renko_pattern_finder.py
renko_pattern_finder-0.0.1.dist-info/METADATA
renko_pattern_finder-0.0.1.dist-info/WHEEL
renko_pattern_finder-0.0.1.dist-info/top_level.txt
renko_pattern_finder-0.0.1.dist-info/RECORD
